README.rst
setup.py
mnemonic/__init__.py
mnemonic/mnemonic.py
mnemonic/secretsharing.py
mnemonic/shamir.py
mnemonic.egg-info/PKG-INFO
mnemonic.egg-info/SOURCES.txt
mnemonic.egg-info/dependency_links.txt
mnemonic.egg-info/not-zip-safe
mnemonic.egg-info/requires.txt
mnemonic.egg-info/top_level.txt
mnemonic/wordlist/english.txt
mnemonic/wordlist/japanese.txt